asdl.py
asdl-0.1.5.dist-info/RECORD
asdl-0.1.5.dist-info/DESCRIPTION.rst
asdl-0.1.5.dist-info/top_level.txt
asdl-0.1.5.dist-info/metadata.json
asdl-0.1.5.dist-info/WHEEL
asdl-0.1.5.dist-info/METADATA
