Metadata-Version: 2.0
Name: asdl
Version: 0.1.5
Summary: A copy of the ASDL parser used in CPython 3.5.
Home-page: https://github.com/fpoli/python-asdl
Author: Federico Poli
Author-email: federpoli@gmail.com
License: PSFL
Platform: UNKNOWN
Classifier: Development Status :: 4 - Beta
Classifier: Intended Audience :: Developers
Classifier: Topic :: Software Development :: Code Generators
Classifier: Topic :: Software Development :: Compilers
Classifier: License :: OSI Approved :: Python Software Foundation License
Classifier: Operating System :: OS Independent
Classifier: Programming Language :: Python :: 2
Classifier: Programming Language :: Python :: 2.7
Classifier: Programming Language :: Python :: 3
Classifier: Programming Language :: Python :: 3.2
Classifier: Programming Language :: Python :: 3.3
Classifier: Programming Language :: Python :: 3.4
Classifier: Programming Language :: Python :: 3.5
Provides-Extra: dev
Requires-Dist: twine; extra == 'dev'
Requires-Dist: nose; extra == 'dev'
Requires-Dist: pep8 (==1.4.6); extra == 'dev'
